Workbook

Sheet 00_Cover
B2: NORTHLINE CONSUMER PRODUCTS
B3: Board / ELT Flash — Monthly Close One-Pager
B4: Fictional CPG portfolio sample · figures in $000s · formulas only (no VBA)
B6: Purpose
B7: A print-ready ELT flash you can put in front of the executive team five minutes after close. Actual vs Budget vs Forecast for the close month and YTD, board KPIs with RAG, and structured callouts.
B9: How to use
B10: 1. Open 01_Assumptions — set the close month and edit headline drivers (yellow / blue).
B11: 2. Review 02_P&L_Flash — Actual / Budget / Forecast for month and YTD ($ and %).
B12: 3. Check 03_KPIs — 7 board KPIs with RAG vs plan.
B13: 4. Update 04_Callouts — yellow commentary boxes for the ELT narrative.
B14: 5. Print / PDF 05_One_Pager — the money tab. One landscape page for the ELT pack.
B16: Color convention
B17: Yellow fill + blue font | C17: =inputs (edit these)
B18: Black font | C18: =formulas (do not overwrite)
B19: Green / Amber / Red | C19: =RAG status (formula-driven)
B21: Tabs
B22: 00_Cover | C22: Purpose and navigation
B23: 01_Assumptions | C23: Close month, headlines, RAG bands
B24: 02_P&L_Flash | C24: P&L Actual / Budget / Forecast — $ and %
B25: 03_KPIs | C25: Board KPIs with RAG
B26: 04_Callouts | C26: ELT commentary inputs
B27: 05_One_Pager | C27: Print-ready one-pager (the money tab)
B28: 06_Data_Dictionary | C28: Field definitions
B30: Sai Siri Bandaru — Financial Analyst | FP&A | forecasting, variance analysis, Excel
B31: All sample numbers are fictional. No employer data.

Sheet 01_Assumptions
B2: 01 · Assumptions
B3: Yellow cells are inputs. Close month drives INDEX lookups on the P&L and one-pager.
B5: Reporting
B6: Close month (1–12) | C6: 8 | D6: =IF(OR(C6<1,C6>12),"Check month",INDEX({"Jan","Feb","Mar","Apr","May","Jun","Jul","Aug","Sep","Oct","Nov","Dec"},C6)&"-26") | E6: ← displayed label
B7: Fiscal year | C7: FY26
B8: Company | C8: Northline Consumer Products
B9: Units | C9: $000s
B10: Prepared by | C10: FP&A
B11: As-of date | C11: 2026-09-03
B13: Headlines (edit for the pack)
B14: Headline 1 | C14: Revenue +0.9% vs budget in Aug; YTD +0.9% — volume and mix both ahead.
B15: Headline 2 | C15: Gross margin 42.4% vs 43.0% budget — commodity and freight pressure, partially offset by price.
B16: Headline 3 | C16: EBITDA $11.2M vs $10.8M budget (+4.1%) — opex discipline and lower scrap.
B17: Headline 4 | C17: Cash conversion solid; DSO 41 days (−1 vs plan). Capex on track.
B18: Watch item | C18: Q4 promo calendar heavy — protect AUR and trade spend ROI.
B20: RAG bands (board KPIs)
B21: KPI | C21: Direction | D21: Amber band | E21: Green band | F21: Notes
B22: Net revenue vs budget | C22: H | D22: 0.02 | E22: 0 | F22: Green if ≥ budget; Amber if within −2%
B23: Gross margin % | C23: H | D23: 0.015 | E23: 0.005 | F23: pp vs budget
B24: EBITDA vs budget | C24: H | D24: 0.05 | E24: 0 | F24: Green if ≥ budget
B25: Volume (000 cases) | C25: H | D25: 0.03 | E25: 0 | F25: vs budget
B26: OTIF % | C26: H | D26: 0.02 | E26: 0.01 | F26: On-time in-full
B27: DSO (days) | C27: L | D27: 0.05 | E27: 0.02 | F27: Lower better
B28: Operating cash flow | C28: H | D28: 0.08 | E28: 0 | F28: vs budget
B30: Direction: H = higher-better, L = lower-better. Bands are relative to plan.

Sheet 02_P&L_Flash
B2: 02 · P&L Flash
B3: ='01_Assumptions'!D6&" close · Actual / Budget / Forecast · $000s"
C5: Close month | H5: YTD | N5: Gross margin %
B6: Line | C6: Actual | D6: Budget | E6: Forecast | F6: A vs B % | G6: A vs F % | H6: Actual | I6: Budget | J6: Forecast | K6: A vs B % | L6: A vs F % | N6: Mo Act GM%
B7: Net revenue | C7: 80500 | D7: 79800 | E7: 81000 | F7: =IF(D7=0,0,(C7-D7)/ABS(D7)) | G7: =IF(E7=0,0,(C7-E7)/ABS(E7)) | H7: 604100 | I7: 598800 | J7: 606500 | K7: =IF(I7=0,0,(H7-I7)/ABS(I7)) | L7: =IF(J7=0,0,(H7-J7)/ABS(J7)) | N7: =IF(C7=0,0,C9/C7)
B8: Cost of goods sold | C8: 46370 | D8: 45486 | E8: 46200 | F8: =IF(D8=0,0,(C8-D8)/ABS(D8)) | G8: =IF(E8=0,0,(C8-E8)/ABS(E8)) | H8: 348500 | I8: 343200 | J8: 347800 | K8: =IF(I8=0,0,(H8-I8)/ABS(I8)) | L8: =IF(J8=0,0,(H8-J8)/ABS(J8)) | N8: Mo Bud GM%
B9: Gross profit | C9: =C7-C8 | D9: =D7-D8 | E9: =E7-E8 | F9: =IF(D9=0,0,(C9-D9)/ABS(D9)) | G9: =IF(E9=0,0,(C9-E9)/ABS(E9)) | H9: =H7-H8 | I9: =I7-I8 | J9: =J7-J8 | K9: =IF(I9=0,0,(H9-I9)/ABS(I9)) | L9: =IF(J9=0,0,(H9-J9)/ABS(J9)) | N9: =IF(D7=0,0,D9/D7)
B10: SG&A | C10: 15050 | D10: 14763 | E10: 14900 | F10: =IF(D10=0,0,(C10-D10)/ABS(D10)) | G10: =IF(E10=0,0,(C10-E10)/ABS(E10)) | H10: 113200 | I10: 110800 | J10: 112400 | K10: =IF(I10=0,0,(H10-I10)/ABS(I10)) | L10: =IF(J10=0,0,(H10-J10)/ABS(J10))
B11: Marketing & trade | C11: 6450 | D11: 6384 | E11: 6500 | F11: =IF(D11=0,0,(C11-D11)/ABS(D11)) | G11: =IF(E11=0,0,(C11-E11)/ABS(E11)) | H11: 48600 | I11: 47900 | J11: 49000 | K11: =IF(I11=0,0,(H11-I11)/ABS(I11)) | L11: =IF(J11=0,0,(H11-J11)/ABS(J11))
B12: R&D / innovation | C12: 2415 | D12: 2394 | E12: 2400 | F12: =IF(D12=0,0,(C12-D12)/ABS(D12)) | G12: =IF(E12=0,0,(C12-E12)/ABS(E12)) | H12: 18200 | I12: 17950 | J12: 18100 | K12: =IF(I12=0,0,(H12-I12)/ABS(I12)) | L12: =IF(J12=0,0,(H12-J12)/ABS(J12))
B13: Total opex | C13: =C10+C11+C12 | D13: =D10+D11+D12 | E13: =E10+E11+E12 | F13: =IF(D13=0,0,(C13-D13)/ABS(D13)) | G13: =IF(E13=0,0,(C13-E13)/ABS(E13)) | H13: =H10+H11+H12 | I13: =I10+I11+I12 | J13: =J10+J11+J12 | K13: =IF(I13=0,0,(H13-I13)/ABS(I13)) | L13: =IF(J13=0,0,(H13-J13)/ABS(J13))
B14: EBITDA | C14: =C9-C13 | D14: =D9-D13 | E14: =E9-E13 | F14: =IF(D14=0,0,(C14-D14)/ABS(D14)) | G14: =IF(E14=0,0,(C14-E14)/ABS(E14)) | H14: =H9-H13 | I14: =I9-I13 | J14: =J9-J13 | K14: =IF(I14=0,0,(H14-I14)/ABS(I14)) | L14: =IF(J14=0,0,(H14-J14)/ABS(J14))
B15: D&A | C15: 3220 | D15: 3192 | E15: 3200 | F15: =IF(D15=0,0,(C15-D15)/ABS(D15)) | G15: =IF(E15=0,0,(C15-E15)/ABS(E15)) | H15: 24160 | I15: 23940 | J15: 24080 | K15: =IF(I15=0,0,(H15-I15)/ABS(I15)) | L15: =IF(J15=0,0,(H15-J15)/ABS(J15))
B16: EBIT | C16: =C14-C15 | D16: =D14-D15 | E16: =E14-E15 | F16: =IF(D16=0,0,(C16-D16)/ABS(D16)) | G16: =IF(E16=0,0,(C16-E16)/ABS(E16)) | H16: =H14-H15 | I16: =I14-I15 | J16: =J14-J15 | K16: =IF(I16=0,0,(H16-I16)/ABS(I16)) | L16: =IF(J16=0,0,(H16-J16)/ABS(J16))
B17: Interest expense | C17: 1610 | D17: 1596 | E17: 1600 | F17: =IF(D17=0,0,(C17-D17)/ABS(D17)) | G17: =IF(E17=0,0,(C17-E17)/ABS(E17)) | H17: 12080 | I17: 11970 | J17: 12040 | K17: =IF(I17=0,0,(H17-I17)/ABS(I17)) | L17: =IF(J17=0,0,(H17-J17)/ABS(J17))
B18: EBT | C18: =C16-C17 | D18: =D16-D17 | E18: =E16-E17 | F18: =IF(D18=0,0,(C18-D18)/ABS(D18)) | G18: =IF(E18=0,0,(C18-E18)/ABS(E18)) | H18: =H16-H17 | I18: =I16-I17 | J18: =J16-J17 | K18: =IF(I18=0,0,(H18-I18)/ABS(I18)) | L18: =IF(J18=0,0,(H18-J18)/ABS(J18))
B19: Tax | C19: 2690 | D19: 2895 | E19: 2950 | F19: =IF(D19=0,0,(C19-D19)/ABS(D19)) | G19: =IF(E19=0,0,(C19-E19)/ABS(E19)) | H19: 22300 | I19: 23760 | J19: 24100 | K19: =IF(I19=0,0,(H19-I19)/ABS(I19)) | L19: =IF(J19=0,0,(H19-J19)/ABS(J19))
B20: Net income | C20: =C18-C19 | D20: =D18-D19 | E20: =E18-E19 | F20: =IF(D20=0,0,(C20-D20)/ABS(D20)) | G20: =IF(E20=0,0,(C20-E20)/ABS(E20)) | H20: =H18-H19 | I20: =I18-I19 | J20: =J18-J19 | K20: =IF(I20=0,0,(H20-I20)/ABS(I20)) | L20: =IF(J20=0,0,(H20-J20)/ABS(J20))
B22: Margins (formula)
B23: EBITDA margin % (Mo Act) | C23: =IF(C7=0,0,C14/C7) | D23: vs Bud | E23: =IF(D7=0,0,D14/D7)
B24: EBITDA margin % (YTD Act) | C24: =IF(H7=0,0,H14/H7) | D24: vs Bud | E24: =IF(I7=0,0,I14/I7)
B26: Yellow = paste from the close pack. Green rows = key subtotals (formulas).

Sheet 03_KPIs
B2: 03 · Board KPIs
B3: Seven ELT-facing KPIs for the close month. RAG is formula-driven from Assumptions bands.
B5: KPI | C5: Actual | D5: Budget | E5: Var $ / pp | F5: Var % | G5: RAG | H5: YTD Act | I5: YTD Bud | J5: Commentary
B6: Net revenue ($000s) | C6: 80500 | D6: 79800 | E6: =C6-D6 | F6: =IF(D6=0,0,(C6-D6)/ABS(D6)) | G6: =IF(C6>=D6,"Green",IF(C6>=D6*(1-'01_Assumptions'!D22),"Amber","Red")) | H6: 604100 | I6: 598800 | J6: Volume + mix ahead; AUR slightly soft on promo.
B7: Gross margin % | C7: 0.424 | D7: 0.43 | E7: =C7-D7 | F7: =IF(D7=0,0,(C7-D7)/ABS(D7)) | G7: =IF(C7>=D7,"Green",IF(C7>=D7*(1-'01_Assumptions'!D23),"Amber","Red")) | H7: 0.423 | I7: 0.427 | J7: Commodity + freight; price/mix partially offsets.
B8: EBITDA ($000s) | C8: 11215 | D8: 10773 | E8: =C8-D8 | F8: =IF(D8=0,0,(C8-D8)/ABS(D8)) | G8: =IF(C8>=D8,"Green",IF(C8>=D8*(1-'01_Assumptions'!D24),"Amber","Red")) | H8: 84100 | I8: 82150 | J8: Opex discipline and lower scrap vs plan.
B9: Volume (000 cases) | C9: 6720 | D9: 6650 | E9: =C9-D9 | F9: =IF(D9=0,0,(C9-D9)/ABS(D9)) | G9: =IF(C9>=D9,"Green",IF(C9>=D9*(1-'01_Assumptions'!D25),"Amber","Red")) | H9: 50340 | I9: 49900 | J9: Club and e-comm channels lead.
B10: OTIF % | C10: 0.961 | D10: 0.97 | E10: =C10-D10 | F10: =IF(D10=0,0,(C10-D10)/ABS(D10)) | G10: =IF(C10>=D10,"Green",IF(C10>=D10*(1-'01_Assumptions'!D26),"Amber","Red")) | H10: 0.966 | I10: 0.97 | J10: West DC labor constraints in week 3.
B11: DSO (days) | C11: 41.2 | D11: 42 | E11: =C11-D11 | F11: =IF(D11=0,0,(C11-D11)/ABS(D11)) | G11: =IF(C11<=D11,"Green",IF(C11<=D11*(1+'01_Assumptions'!D27),"Amber","Red")) | H11: 41.2 | I11: 42 | J11: Collections strong; retail terms stable.
B12: Op. cash flow ($000s) | C12: 6200 | D12: 5800 | E12: =C12-D12 | F12: =IF(D12=0,0,(C12-D12)/ABS(D12)) | G12: =IF(C12>=D12,"Green",IF(C12>=D12*(1-'01_Assumptions'!D28),"Amber","Red")) | H12: 47300 | I12: 45100 | J12: Working capital release + EBITDA beat.
B14: Summary counts
B15: Green | C15: =COUNTIF(G6:G12,"Green") | D15: Amber | E15: =COUNTIF(G6:G12,"Amber") | F15: Red | G15: =COUNTIF(G6:G12,"Red")
B17: Edit Actual / Budget (yellow). RAG and variance recalculate automatically.

Sheet 04_Callouts
B2: 04 · Callouts
B3: Structured commentary for the ELT pack. Everything yellow is an input — keep it tight.
B5: What went well
B6: • | C6: EBITDA beat budget by $0.4M in-month; YTD beat $2.0M.
B7: • | C7: DSO improved 0.8 days vs plan; collections cadence holding.
B8: • | C8: Club channel volume +6% vs budget; e-comm contribution margin expanding.
B10: What needs attention
B11: • | C11: Gross margin −0.6 pp vs budget — resin and inbound freight.
B12: • | C12: OTIF 96.1% vs 97.0% target — West DC temp labor gap in week 3.
B13: • | C13: Trade spend pacing ahead of plan in Club; ROI review in flight.
B15: Decisions / asks
B16: • | C16: Approve Q4 promo guardrails (AUR floor + trade ROI hurdle).
B17: • | C17: Authorize West DC overtime / temp surge through peak (est. $180k).
B18: • | C18: Confirm commodity hedge window for Q1 resin (Treasury + Procurement).
B20: Risks & mitigations
B21: • | C21: Q4 promo intensity — mitigate with SKU-level AUR floors and sell-in caps.
B22: • | C22: Freight lane volatility — dual-source West inbound; lock 60-day rates.
B23: • | C23: Retailer inventory rightsizing — lean into high-velocity SKUs; cut slow movers.
B25: Forward look (next 90 days)
B26: • | C26: Sep flash: hold GM recovery plan (price/mix + freight actions).
B27: • | C27: Oct: board deep-dive on unit economics of launch SKU NL-Probiotic Bar.
B28: • | C28: Nov: FY27 budget kickoff — volume, AUR, and opex envelopes.
B30: Owner / next update | C30: FP&A — next flash 3 business days after Sep close

Sheet 05_One_Pager
B1: ="NORTHLINE · ELT FLASH · "&'01_Assumptions'!D6&" "&'01_Assumptions'!C7
B2: ='01_Assumptions'!C8&" · $000s · Prepared by "&'01_Assumptions'!C10&" · As-of "&TEXT('01_Assumptions'!C11,"YYYY-MM-DD")
B4: BOARD KPIs
B5: NET REVENUE | D5: GROSS MARGIN | F5: EBITDA | H5: VOLUME | J5: OTIF | L5: DSO (days)
B6: ='03_KPIs'!C6 | D6: ='03_KPIs'!C7 | F6: ='03_KPIs'!C8 | H6: ='03_KPIs'!C9 | J6: ='03_KPIs'!C10 | L6: ='03_KPIs'!C11
B7: ='03_KPIs'!F6 | C7: ='03_KPIs'!G6 | D7: ='03_KPIs'!E7 | E7: ='03_KPIs'!G7 | F7: ='03_KPIs'!F8 | G7: ='03_KPIs'!G8 | H7: ='03_KPIs'!F9 | I7: ='03_KPIs'!G9 | J7: ='03_KPIs'!F10 | K7: ='03_KPIs'!G10 | L7: ='03_KPIs'!E11 | M7: ='03_KPIs'!G11
B9: P&L FLASH ($000s) | I9: HEADLINES
B10: Line | C10: Mo Act | D10: Mo Bud | E10: A vs B % | F10: YTD Act | G10: YTD A vs B % | H10: H1 | I10: ='01_Assumptions'!C14
B11: Net revenue | C11: ='02_P&L_Flash'!C7 | D11: ='02_P&L_Flash'!D7 | E11: ='02_P&L_Flash'!F7 | F11: ='02_P&L_Flash'!H7 | G11: ='02_P&L_Flash'!K7 | H11: H2 | I11: ='01_Assumptions'!C15
B12: Gross profit | C12: ='02_P&L_Flash'!C9 | D12: ='02_P&L_Flash'!D9 | E12: ='02_P&L_Flash'!F9 | F12: ='02_P&L_Flash'!H9 | G12: ='02_P&L_Flash'!K9 | H12: H3 | I12: ='01_Assumptions'!C16
B13: EBITDA | C13: ='02_P&L_Flash'!C14 | D13: ='02_P&L_Flash'!D14 | E13: ='02_P&L_Flash'!F14 | F13: ='02_P&L_Flash'!H14 | G13: ='02_P&L_Flash'!K14 | H13: H4 | I13: ='01_Assumptions'!C17
B14: EBIT | C14: ='02_P&L_Flash'!C16 | D14: ='02_P&L_Flash'!D16 | E14: ='02_P&L_Flash'!F16 | F14: ='02_P&L_Flash'!H16 | G14: ='02_P&L_Flash'!K16 | H14: WATCH | I14: ='01_Assumptions'!C18
B15: Net income | C15: ='02_P&L_Flash'!C20 | D15: ='02_P&L_Flash'!D20 | E15: ='02_P&L_Flash'!F20 | F15: ='02_P&L_Flash'!H20 | G15: ='02_P&L_Flash'!K20
B17: GM% Mo | C17: ='02_P&L_Flash'!N7 | D17: EBITDA% Mo | E17: ='02_P&L_Flash'!C23 | F17: EBITDA% YTD | G17: ='02_P&L_Flash'!C24
B19: CALLOUTS (from 04) | I19: RAG SCOREBOARD
B20: Well | C20: ='04_Callouts'!C6 | I20: Green | J20: ='03_KPIs'!C15 | K20: Amber | L20: ='03_KPIs'!E15
B21: Watch | C21: ='04_Callouts'!C11 | I21: Red | J21: ='03_KPIs'!G15 | K21: KPIs | L21: =J20+L20+J21
B22: Ask | C22: ='04_Callouts'!C16 | I22: Cash RAG | J22: ='03_KPIs'!G12
B23: Risk | C23: ='04_Callouts'!C21 | I23: OCF Mo Act | J23: ='03_KPIs'!C12
B24: Print this sheet landscape · 1 page · Yellow inputs live on Assumptions / P&L / KPIs / Callouts · Fictional sample
I25: Chart data (Mo Act vs Bud)
I26: Line | J26: Actual | K26: Budget
I27: Revenue | J27: ='02_P&L_Flash'!C7 | K27: ='02_P&L_Flash'!D7
I28: GP | J28: ='02_P&L_Flash'!C9 | K28: ='02_P&L_Flash'!D9
I29: EBITDA | J29: ='02_P&L_Flash'!C14 | K29: ='02_P&L_Flash'!D14

Sheet 06_Data_Dictionary
B2: 06 · Data Dictionary
B3: Field definitions so another analyst can inherit the file.
B5: Field | C5: Tab | D5: Definition
B6: Close month | C6: 01_Assumptions | D6: 1–12 toggle. Labels the flash period and drives the one-pager banner.
B7: Headlines 1–4 + Watch | C7: 01_Assumptions | D7: ELT narrative bullets. Flow to 05_One_Pager.
B8: RAG bands | C8: 01_Assumptions | D8: Amber / Green relative bands by KPI. Direction H = higher-better, L = lower-better.
B9: P&L Actual / Budget / Forecast | C9: 02_P&L_Flash | D9: Close-month and YTD $000s. Yellow inputs for leaf lines; subtotals are formulas.
B10: A vs B % / A vs F % | C10: 02_P&L_Flash | D10: (Actual − Plan) / |Plan|. Conditional formatting: green ≥0.5%, amber −2% to 0.5%, red < −2%.
B11: Gross profit / EBITDA / EBIT / NI | C11: 02_P&L_Flash | D11: Formula subtotals. Green-highlighted key rows.
B12: Gross margin % | C12: 02_P&L_Flash | D12: Gross profit ÷ net revenue.
B13: EBITDA margin % | C13: 02_P&L_Flash | D13: EBITDA ÷ net revenue — month and YTD.
B14: Board KPIs | C14: 03_KPIs | D14: Seven ELT KPIs: revenue, GM%, EBITDA, volume, OTIF, DSO, operating cash flow.
B15: KPI RAG | C15: 03_KPIs | D15: Green / Amber / Red from actual vs budget and Assumptions bands. Formula, not typed.
B16: Callouts | C16: 04_Callouts | D16: What went well, attention, decisions/asks, risks, forward look — yellow commentary.
... B19: Color convention | C19: All | D19: Yellow + blue font = inputs. Black font = formulas. Green/Amber/Red = RAG.
B21: All sample numbers are fictional. Built for a public GitHub portfolio — no employer data.
